bb_projects_calc/__init__.py
bb_projects_calc/action/__init__.py
bb_projects_calc/action/add_action.py
bb_projects_calc/action/mul_action.py
bb_projects_calc/app.py
bb_projects_calc/operations.py
bb_projects_calc-0.2.0.dist-info/METADATA
bb_projects_calc-0.2.0.dist-info/WHEEL
bb_projects_calc-0.2.0.dist-info/RECORD
